{
  "main": {
    "id": "d7cf628034c1e934",
    "type": "split",
    "children": [
      {
        "id": "b06aaa23614b3736",
        "type": "tabs",
        "children": [
          {
            "id": "7a1b4f9326683855",
            "type": "leaf",
            "state": {
              "type": "markdown",
              "state": {
                "file": "CTF32 - Hunter/CTF32 - Hunter.md",
                "mode": "source",
                "source": false
              }
            }
          },
          {
            "id": "64adfcf2012c05f2",
            "type": "leaf",
            "state": {
              "type": "markdown",
              "state": {
                "file": "CTF34 - Spotlight/CTF34 - Spotlight.md",
                "mode": "source",
                "source": false
              }
            }
          },
          {
            "id": "ef1b3e5c21498246",
            "type": "leaf",
            "state": {
              "type": "markdown",
              "state": {
                "file": "CTF68 - PacketMaze/CTF68 - PacketMaze.md",
                "mode": "source",
                "source": false
              }
            }
          },
          {
            "id": "cf1369a7cfc3f267",
            "type": "leaf",
            "state": {
              "type": "markdown",
              "state": {
                "file": "CTF39 - QRadar101/CTF39 - QRadar101.md",
                "mode": "source",
                "source": false
              }
            }
          }
        ],
        "currentTab": 3
      }
    ],
    "direction": "vertical"
  },
  "left": {
    "id": "3991b9f0c7313622",
    "type": "split",
    "children": [
      {
        "id": "0f272b3c3454d968",
        "type": "tabs",
        "children": [
          {
            "id": "3ad07ab353c48e9a",
            "type": "leaf",
            "state": {
              "type": "file-explorer",
              "state": {
                "sortOrder": "alphabetical"
              }
            }
          },
          {
            "id": "29007ea1f4f63583",
            "type": "leaf",
            "state": {
              "type": "search",
              "state": {
                "query": "",
                "matchingCase": false,
                "explainSearch": false,
                "collapseAll": false,
                "extraContext": false,
                "sortOrder": "alphabetical"
              }
            }
          },
          {
            "id": "ed5e0386ae98b51c",
            "type": "leaf",
            "state": {
              "type": "bookmarks",
              "state": {}
            }
          }
        ]
      }
    ],
    "direction": "horizontal",
    "width": 200
  },
  "right": {
    "id": "fed9740cac770776",
    "type": "split",
    "children": [
      {
        "id": "46a8259e93fefd1d",
        "type": "tabs",
        "children": [
          {
            "id": "d8f23e53270706bf",
            "type": "leaf",
            "state": {
              "type": "backlink",
              "state": {
                "file": "CTF39 - QRadar101/CTF39 - QRadar101.md",
                "collapseAll": false,
                "extraContext": false,
                "sortOrder": "alphabetical",
                "showSearch": false,
                "searchQuery": "",
                "backlinkCollapsed": false,
                "unlinkedCollapsed": true
              }
            }
          },
          {
            "id": "bac6030e87e3e852",
            "type": "leaf",
            "state": {
              "type": "outgoing-link",
              "state": {
                "file": "CTF39 - QRadar101/CTF39 - QRadar101.md",
                "linksCollapsed": false,
                "unlinkedCollapsed": true
              }
            }
          },
          {
            "id": "71513b8e6ee547bc",
            "type": "leaf",
            "state": {
              "type": "tag",
              "state": {
                "sortOrder": "frequency",
                "useHierarchy": true
              }
            }
          },
          {
            "id": "b09a253b5c5fe15f",
            "type": "leaf",
            "state": {
              "type": "outline",
              "state": {
                "file": "CTF39 - QRadar101/CTF39 - QRadar101.md"
              }
            }
          }
        ]
      }
    ],
    "direction": "horizontal",
    "width": 300,
    "collapsed": true
  },
  "left-ribbon": {
    "hiddenItems": {
      "switcher:Open quick switcher": false,
      "graph:Open graph view": false,
      "canvas:Create new canvas": false,
      "daily-notes:Open today's daily note": false,
      "templates:Insert template": false,
      "command-palette:Open command palette": false
    }
  },
  "active": "cf1369a7cfc3f267",
  "lastOpenFiles": [
    "CTF39 - QRadar101/Pictures/Question_21.png",
    "CTF39 - QRadar101/CTF39 - QRadar101.md",
    "CTF39 - QRadar101/Pictures/Question_22.png",
    "CTF39 - QRadar101/Pictures/Question_20.png",
    "CTF39 - QRadar101/Pictures/Question_18.png",
    "CTF39 - QRadar101/Pictures/Question_19.png",
    "CTF39 - QRadar101/Pictures/Question_15.png",
    "CTF39 - QRadar101/Pictures/Question_14.png",
    "CTF39 - QRadar101/Pictures/Question_13.png",
    "CTF39 - QRadar101/Pictures/Question_12.png",
    "CTF39 - QRadar101/Pictures/Question_5.png",
    "CTF34 - Spotlight/CTF34 - Spotlight.md",
    "CTF44 - NukeTheBrowser/CTF44 - NukeTheBrowser.md",
    "CTF39 - QRadar101/Pictures",
    "CTF39 - QRadar101",
    "CTF44 - NukeTheBrowser/Code_extraction/spreadsheet.dat.nam",
    "CTF44 - NukeTheBrowser/Code_extraction/spreadsheet.dat.id1",
    "CTF44 - NukeTheBrowser/Code_extraction/spreadsheet.dat.id0",
    "CTF44 - NukeTheBrowser/Code_extraction/spreadsheet.dat",
    "CTF44 - NukeTheBrowser/Code_extraction/Non confirmé 707446.crdownload",
    "CTF44 - NukeTheBrowser/Code_extraction/com.dat",
    "CTF44 - NukeTheBrowser/Code_extraction/Non confirmé 728563.crdownload",
    "CTF44 - NukeTheBrowser/Code_extraction/directshow.dat",
    "CTF32 - Hunter/CTF32 - Hunter.md",
    "README.md",
    "CTF68 - PacketMaze/CTF68 - PacketMaze.md",
    "Question_10.md",
    "Pasted image 20231204162320.png.md"
  ]
}